{
  "animes": [
    {
      "titre": "The strongest job is apparently not a hero or a sage, but an appraiser (provisional)!",
      "titreJp": "",
      "img": "hnxbm",
      "ahId": "rf6nw",
      "addedAt": "2026-04-18T16:07:34.851Z"
    },
    {
      "titre": "Yowayowa Teacher",
      "titreJp": "",
      "img": "b6f8i",
      "ahId": "ayudj",
      "addedAt": "2026-04-18T16:07:34.851Z"
    },
    {
      "titre": "Detective Conan",
      "titreJp": "",
      "img": "lx86z",
      "ahId": "pijt4",
      "addedAt": "2026-04-18T16:07:34.851Z"
    },
    {
      "titre": "Welcome to Demon School, Iruma-kun 4",
      "titreJp": "",
      "img": "lkpy4",
      "ahId": "y9prb",
      "addedAt": "2026-04-18T16:07:34.851Z"
    },
    {
      "titre": "Ascendance of a Bookworm Season 4",
      "titreJp": "",
      "img": "2m22z",
      "ahId": "amsff",
      "addedAt": "2026-04-18T16:07:34.851Z"
    },
    {
      "titre": "Pokemon Horizons: The Series",
      "titreJp": "",
      "img": "9fsft",
      "ahId": "yeyrm",
      "addedAt": "2026-04-18T16:07:34.851Z"
    },
    {
      "titre": "That Time I Got Reincarnated as a Slime Season 4",
      "titreJp": "",
      "img": "pjoyd",
      "ahId": "9v661",
      "addedAt": "2026-04-18T16:07:34.851Z"
    },
    {
      "titre": "Botan Kamiina Fully Blossoms When Drunk",
      "titreJp": "",
      "img": "sbyve",
      "ahId": "fpnp2",
      "addedAt": "2026-04-18T16:07:34.851Z"
    },
    {
      "titre": "The Drops of God",
      "titreJp": "",
      "img": "par8w",
      "ahId": "b0vsk",
      "addedAt": "2026-04-18T16:07:34.851Z"
    },
    {
      "titre": "Snowball Earth",
      "titreJp": "",
      "img": "g0kk7",
      "ahId": "m2zjn",
      "addedAt": "2026-04-18T16:07:34.851Z"
    },
    {
      "titre": "That Time I Got Reincarnated as a Slime Season 4",
      "titreJp": "",
      "img": "pjoyd",
      "ahId": "3kfyx",
      "addedAt": "2026-04-18T16:07:34.851Z"
    },
    {
      "titre": "An Observation Log of My Fiancée Who Calls Herself a Villainess",
      "titreJp": "",
      "img": "8ezmn",
      "ahId": "ttcnk",
      "addedAt": "2026-04-18T16:07:34.851Z"
    },
    {
      "titre": "All You Need Is Kill",
      "titreJp": "",
      "img": "4kuek",
      "ahId": "nv9bp",
      "addedAt": "2026-04-18T16:07:34.851Z"
    },
    {
      "titre": "Monster Eater",
      "titreJp": "",
      "img": "anfea",
      "ahId": "hev47",
      "addedAt": "2026-04-18T16:07:34.851Z"
    },
    {
      "titre": "Killed Again, Mr. Detective?",
      "titreJp": "",
      "img": "j0cec",
      "ahId": "pi6yi",
      "addedAt": "2026-04-18T16:07:34.851Z"
    },
    {
      "titre": "Haibara’s Teenage New Game+",
      "titreJp": "",
      "img": "dw9gn",
      "ahId": "0cwi8",
      "addedAt": "2026-04-18T16:07:34.851Z"
    },
    {
      "titre": "A Hundred Scenes of AWAJIMA",
      "titreJp": "",
      "img": "r7ozz",
      "ahId": "7s4ze",
      "addedAt": "2026-04-18T16:07:34.851Z"
    },
    {
      "titre": "Petals of Reincarnation",
      "titreJp": "",
      "img": "iideg",
      "ahId": "oh0q2",
      "addedAt": "2026-04-18T16:07:34.851Z"
    },
    {
      "titre": "Kirio Fan Club",
      "titreJp": "",
      "img": "f7jfv",
      "ahId": "b2ybn",
      "addedAt": "2026-04-18T16:07:34.851Z"
    },
    {
      "titre": "The Ramparts of Ice",
      "titreJp": "",
      "img": "cs30h",
      "ahId": "ji7g1",
      "addedAt": "2026-04-18T16:07:34.851Z"
    },
    {
      "titre": "Dr. Stone: Science Future - Part III",
      "titreJp": "",
      "img": "oxfds",
      "ahId": "jx2jr",
      "addedAt": "2026-04-18T16:07:34.851Z"
    },
    {
      "titre": "Kujima: Why Sing, When You Can Warble?",
      "titreJp": "",
      "img": "pv8qk",
      "ahId": "xvd0a",
      "addedAt": "2026-04-18T16:07:34.851Z"
    },
    {
      "titre": "The Barbarian&#039;s Bride",
      "titreJp": "",
      "img": "synxi",
      "ahId": "gbdj0",
      "addedAt": "2026-04-18T16:07:34.851Z"
    },
    {
      "titre": "Record of Grancrest War",
      "titreJp": "",
      "img": "1zf4l",
      "ahId": "hi6b1",
      "addedAt": "2026-04-18T16:07:34.851Z"
    },
    {
      "titre": "Go For It, Nakamura!",
      "titreJp": "",
      "img": "rf7eh",
      "ahId": "lv7v8",
      "addedAt": "2026-04-18T16:07:34.851Z"
    },
    {
      "titre": "The Beginning After the End Season 2",
      "titreJp": "",
      "img": "zmy4z",
      "ahId": "1ijne",
      "addedAt": "2026-04-18T16:07:34.851Z"
    },
    {
      "titre": "Always a Catch!",
      "titreJp": "",
      "img": "r9hz4",
      "ahId": "fv1vj",
      "addedAt": "2026-04-18T16:07:34.851Z"
    },
    {
      "titre": "Gals Can’t Be Kind to Otaku!?",
      "titreJp": "",
      "img": "j5umi",
      "ahId": "frlld",
      "addedAt": "2026-04-18T16:07:34.851Z"
    },
    {
      "titre": "Reborn as a Vending Machine, I Now Wander the Dungeon 3rd Season",
      "titreJp": "",
      "img": "cirfw",
      "ahId": "kq3pz",
      "addedAt": "2026-04-18T16:07:34.851Z"
    },
    {
      "titre": "Dorohedoro 2",
      "titreJp": "",
      "img": "t71fe",
      "ahId": "5iqzo",
      "addedAt": "2026-04-18T16:07:34.851Z"
    },
    {
      "titre": "Re:ZERO: Starting Life in Another World Season 4",
      "titreJp": "",
      "img": "7tc0j",
      "ahId": "pgjgh",
      "addedAt": "2026-04-18T16:07:34.851Z"
    },
    {
      "titre": "Rent-a-Girlfriend Season 5",
      "titreJp": "",
      "img": "7nqj7",
      "ahId": "ilp9j",
      "addedAt": "2026-04-18T16:07:34.851Z"
    },
    {
      "titre": "Classroom of the Elite 4th Season",
      "titreJp": "",
      "img": "npea5",
      "ahId": "i0kd0",
      "addedAt": "2026-04-18T16:07:34.851Z"
    },
    {
      "titre": "My Ribdiculous Reincarnation",
      "titreJp": "",
      "img": "27pp6",
      "ahId": "nzwhr",
      "addedAt": "2026-04-18T16:07:34.851Z"
    },
    {
      "titre": "Pardon the Intrusion, I&#039;m Home!",
      "titreJp": "",
      "img": "mwvn6",
      "ahId": "xw4de",
      "addedAt": "2026-04-18T16:07:34.851Z"
    },
    {
      "titre": "Beyond Twilight",
      "titreJp": "",
      "img": "0gwes",
      "ahId": "c3nol",
      "addedAt": "2026-04-18T16:07:34.851Z"
    },
    {
      "titre": "Eren the Southpaw",
      "titreJp": "",
      "img": "w5epl",
      "ahId": "r32sr",
      "addedAt": "2026-04-18T16:07:34.851Z"
    },
    {
      "titre": "I Made Friends with the Second Prettiest Girl in My Class",
      "titreJp": "",
      "img": "kfuf2",
      "ahId": "j26hl",
      "addedAt": "2026-04-18T16:07:34.851Z"
    },
    {
      "titre": "Marriagetoxin",
      "titreJp": "",
      "img": "ljkt9",
      "ahId": "3c38p",
      "addedAt": "2026-04-18T16:07:34.851Z"
    },
    {
      "titre": "I Want to End This Love Game",
      "titreJp": "",
      "img": "438x1",
      "ahId": "lf9gt",
      "addedAt": "2026-04-18T16:07:34.851Z"
    },
    {
      "titre": "Even a Replica Can Fall in Love",
      "titreJp": "",
      "img": "z35jq",
      "ahId": "jrvi5",
      "addedAt": "2026-04-18T16:07:34.851Z"
    },
    {
      "titre": "The Most Heretical Last Boss Queen: From Villainess to Savior 2nd Season",
      "titreJp": "",
      "img": "5zcck",
      "ahId": "k662x",
      "addedAt": "2026-04-18T16:07:34.851Z"
    },
    {
      "titre": "Magical Sisters Lulutto Lilly",
      "titreJp": "",
      "img": "g8cab",
      "ahId": "np9nt",
      "addedAt": "2026-04-18T16:07:34.851Z"
    },
    {
      "titre": "Release That Witch",
      "titreJp": "",
      "img": "54d5g",
      "ahId": "gnqba",
      "addedAt": "2026-04-18T16:07:34.851Z"
    },
    {
      "titre": "Liar Game",
      "titreJp": "",
      "img": "csbrl",
      "ahId": "fwe7e",
      "addedAt": "2026-04-18T16:07:34.851Z"
    },
    {
      "titre": "The Klutzy Class Monitor and the Girl with the Short Skirt",
      "titreJp": "",
      "img": "jh4do",
      "ahId": "l3kxg",
      "addedAt": "2026-04-18T16:07:34.851Z"
    },
    {
      "titre": "Witch Hat Atelier",
      "titreJp": "",
      "img": "6rlo7",
      "ahId": "fcmyo",
      "addedAt": "2026-04-18T16:07:34.851Z"
    },
    {
      "titre": "Farming Life in Another World 2",
      "titreJp": "",
      "img": "b7en4",
      "ahId": "df4in",
      "addedAt": "2026-04-18T16:07:34.851Z"
    },
    {
      "titre": "Ingoku Danchi: Deviant&#039;s Apartment Complex",
      "titreJp": "",
      "img": "4gqwj",
      "ahId": "fae6d",
      "addedAt": "2026-04-18T16:07:34.851Z"
    },
    {
      "titre": "Marika&#039;s Love Meter Malfunction",
      "titreJp": "",
      "img": "33vsk",
      "ahId": "bgi3j",
      "addedAt": "2026-04-18T16:07:34.851Z"
    },
    {
      "titre": "One Piece",
      "titreJp": "",
      "img": "zbt7y",
      "ahId": "fsi1m",
      "addedAt": "2026-04-18T16:07:34.851Z"
    },
    {
      "titre": "Ghost Concert: Missing Songs",
      "titreJp": "",
      "img": "1ljqb",
      "ahId": "1ht8d",
      "addedAt": "2026-04-18T16:07:34.851Z"
    },
    {
      "titre": "The Classroom of a Black Cat and a Witch",
      "titreJp": "",
      "img": "cs0bn",
      "ahId": "8p2tr",
      "addedAt": "2026-04-18T16:07:34.851Z"
    },
    {
      "titre": "The Food Diary of Miss Maid",
      "titreJp": "",
      "img": "w1qq7",
      "ahId": "7p5hz",
      "addedAt": "2026-04-18T16:07:34.851Z"
    },
    {
      "titre": "Mission: Yozakura Family Season 2",
      "titreJp": "",
      "img": "rgi7x",
      "ahId": "191cx",
      "addedAt": "2026-04-18T16:07:34.851Z"
    },
    {
      "titre": "Ace of the Diamond: Act II 2nd Season",
      "titreJp": "",
      "img": "c50pz",
      "ahId": "feqdi",
      "addedAt": "2026-04-18T16:07:34.851Z"
    },
    {
      "titre": "Wistoria: Wand and Sword 2nd Season",
      "titreJp": "",
      "img": "h6l0c",
      "ahId": "dd464",
      "addedAt": "2026-04-18T16:07:34.851Z"
    },
    {
      "titre": "Rooster Fighter",
      "titreJp": "",
      "img": "vy576",
      "ahId": "y98v5",
      "addedAt": "2026-04-18T16:07:34.851Z"
    },
    {
      "titre": "Digimon Beatbreak",
      "titreJp": "",
      "img": "88ts8",
      "ahId": "uni0y",
      "addedAt": "2026-04-18T16:07:34.851Z"
    },
    {
      "titre": "Ichijouma Mankitsugurashi!",
      "titreJp": "",
      "img": "wm2v7",
      "ahId": "kqa66",
      "addedAt": "2026-04-18T16:07:34.851Z"
    },
    {
      "titre": "Scum of the Brave",
      "titreJp": "",
      "img": "97302",
      "ahId": "ccxi5",
      "addedAt": "2026-04-18T16:07:34.851Z"
    },
    {
      "titre": "Needy Girl Overdose",
      "titreJp": "",
      "img": "57g7m",
      "ahId": "oxx6c",
      "addedAt": "2026-04-18T16:07:34.851Z"
    },
    {
      "titre": "Agents of the Four Seasons: Dance of Spring",
      "titreJp": "",
      "img": "fxza8",
      "ahId": "d696g",
      "addedAt": "2026-04-18T16:07:34.851Z"
    },
    {
      "titre": "Mistress Kanan is Devilishly Easy",
      "titreJp": "",
      "img": "8q6wl",
      "ahId": "boii6",
      "addedAt": "2026-04-18T16:07:34.851Z"
    },
    {
      "titre": "MAO",
      "titreJp": "",
      "img": "topci",
      "ahId": "o8996",
      "addedAt": "2026-04-18T16:50:12.222Z"
    },
    {
      "titre": "Kill Blue",
      "titreJp": "",
      "img": "dns6b",
      "ahId": "qw2g9",
      "addedAt": "2026-04-18T16:50:12.222Z"
    },
    {
      "titre": "The Great Sage Ryddel and the Hands of Time",
      "titreJp": "Kill Ao",
      "img": "tl46m",
      "ahId": "y5v48",
      "addedAt": "2026-04-18T16:50:12.222Z"
    },
    {
      "titre": "Akane-banashi",
      "titreJp": "Yomi no Tsugai",
      "img": "7j7kb",
      "ahId": "pm96z",
      "addedAt": "2026-04-18T17:14:10.582Z"
    },
    {
      "titre": "Agents of the Four Seasons: Dance of Spring",
      "titreJp": "",
      "img": "fxza8",
      "ahId": "z320l",
      "addedAt": "2026-04-18T17:28:22.129Z"
    },
    {
      "titre": "Daemons of The Shadow Realm",
      "titreJp": "Kanan-sama wa Akumade Choroi",
      "img": "dks5o",
      "ahId": "3uz6y",
      "addedAt": "2026-04-18T17:28:22.129Z"
    },
    {
      "titre": "Tensei Shitara Slime Datta Ken Season 4",
      "titreJp": "Tensei Shitara Slime Datta Ken Season 4",
      "img": "c3rqy",
      "ahId": "aplyf",
      "addedAt": "2026-04-18T18:31:49.351Z"
    },
    {
      "titre": "Maid-san wa Taberu dake",
      "titreJp": "Maid-san wa Taberu dake",
      "img": "doqc0",
      "ahId": "7b5z4",
      "addedAt": "2026-04-18T18:31:49.351Z"
    },
    {
      "titre": "Monster",
      "titreJp": "",
      "img": "h1ks9",
      "ahId": "j5ijk",
      "addedAt": "2026-04-21T22:11:16.696Z"
    },
    {
      "titre": "Hanamonogatari",
      "titreJp": "Hanamonogatari: Suruga Devil",
      "img": "odtij",
      "ahId": "jy90a",
      "addedAt": "2026-04-25T17:11:24.074Z"
    },
    {
      "titre": "Koyomimonogatari",
      "titreJp": "",
      "img": "8fypw",
      "ahId": "92o55",
      "addedAt": "2026-04-25T19:57:22.784Z"
    },
    {
      "titre": "Tsukimonogatari",
      "titreJp": "Tsukimonogatari: Yotsugi Doll",
      "img": "drvf7",
      "ahId": "u7fdt",
      "addedAt": "2026-04-25T19:57:22.784Z"
    },
    {
      "titre": "Owarimonogatari",
      "titreJp": "",
      "img": "jvxkc",
      "ahId": "j4rej",
      "addedAt": "2026-04-25T21:55:14.130Z"
    },
    {
      "titre": "Zoku Owarimonogatari",
      "titreJp": "",
      "img": "269oe",
      "ahId": "kjkok",
      "addedAt": "2026-04-25T23:57:22.389Z"
    },
    {
      "titre": "Owarimonogatari II",
      "titreJp": "",
      "img": "vhksv",
      "ahId": "tllm1",
      "addedAt": "2026-04-25T23:57:22.389Z"
    },
    {
      "titre": "Nana",
      "titreJp": "",
      "img": "rwxv9",
      "ahId": "j4pza",
      "addedAt": "2026-04-26T14:10:36.729Z"
    },
    {
      "titre": "My Hero Academia 170+1: More",
      "titreJp": "Boku no Hero Academia 170+1: More",
      "img": "f525x",
      "ahId": "6jhnt",
      "addedAt": "2026-05-02T14:15:39.000Z"
    },
    {
      "titre": "Moriarty the Patriot OVA",
      "titreJp": "Yuukoku no Moriarty OVA",
      "img": "jap39",
      "ahId": "elmct",
      "addedAt": "2026-05-02T14:15:39.000Z"
    },
    {
      "titre": "Land of the Lustrous",
      "titreJp": "Houseki no Kuni",
      "img": "n1ktn",
      "ahId": "urs2p",
      "addedAt": "2026-05-05T00:09:44.724Z"
    },
    {
      "titre": "Fruits Basket 1st Season",
      "titreJp": "Fruits Basket (2019)",
      "img": "089yg",
      "ahId": "glmrm",
      "addedAt": "2026-05-05T12:15:12.313Z"
    },
    {
      "titre": "Toradora!",
      "titreJp": "",
      "img": "a63cz",
      "ahId": "sclkr",
      "addedAt": "2026-05-05T18:01:54.454Z"
    },
    {
      "titre": "91 Days",
      "titreJp": "",
      "img": "836l5",
      "ahId": "yt2vb",
      "addedAt": "2026-05-08T16:57:59.322Z"
    },
    {
      "titre": "OreShura",
      "titreJp": "Ore no Kanojo to Osananajimi ga Shuraba Sugiru",
      "img": "882p5",
      "ahId": "aycau",
      "addedAt": "2026-05-13T17:22:09.589Z"
    },
    {
      "titre": "High School DxD NEW",
      "titreJp": "",
      "img": "cl65y",
      "ahId": "3i16j",
      "addedAt": "2026-05-16T16:12:39.270Z"
    },
    {
      "titre": "Scarlet",
      "titreJp": "Hateshi Naki Scarlet",
      "img": "0wm69",
      "ahId": "n91xy",
      "addedAt": "2026-05-16T20:06:51.519Z"
    },
    {
      "titre": "Black Butler",
      "titreJp": "Kuroshitsuji",
      "img": "i3tgh",
      "ahId": "hbp60",
      "addedAt": "2026-05-16T23:36:40.046Z"
    },
    {
      "titre": "Black Butler 2",
      "titreJp": "Kuroshitsuji 2",
      "img": "bcfzu",
      "ahId": "mkld8",
      "addedAt": "2026-05-17T14:24:23.890Z"
    },
    {
      "titre": "Neon Genesis Evangelion: The End of Evangelion",
      "titreJp": "Shinseiki Evangelion: The End of Evangelion",
      "img": "dalq3",
      "ahId": "4a74y",
      "addedAt": "2026-05-17T20:45:53.941Z"
    },
    {
      "titre": "Black Butler: Book of Circus",
      "titreJp": "Kuroshitsuji: Book of Circus",
      "img": "zeabo",
      "ahId": "mcdda",
      "addedAt": "2026-05-18T15:24:08.393Z"
    },
    {
      "titre": "Boarding School Juliet",
      "titreJp": "Kishuku Gakkou no Juliet",
      "img": "xsnni",
      "ahId": "d171x",
      "addedAt": "2026-05-19T12:06:29.444Z"
    },
    {
      "titre": "Isekai Office Worker: The Other World's Books Depend on the Bean Counter",
      "titreJp": "Isekai no Sata wa Shachiku Shidai",
      "img": "olruf",
      "ahId": "ju9ye",
      "addedAt": "2026-05-28T10:52:44.009Z"
    },
    {
      "titre": "Science Fell in Love, So I Tried to Prove It",
      "titreJp": "Rikei ga Koi ni Ochita no de Shoumei Shitemita.",
      "img": "sod2c",
      "ahId": "l8zc1",
      "addedAt": "2026-05-29T13:57:41.018Z"
    },
    {
      "titre": "Science Fell in Love, So I Tried to Prove It. r=1-sinθ",
      "titreJp": "Rikei ga Koi ni Ochita no de Shoumei Shitemita. r=1-sinθ (Heart)",
      "img": "17ryz",
      "ahId": "7yfa0",
      "addedAt": "2026-05-30T04:50:42.538Z"
    },
    {
      "titre": "Beyond the Boundary",
      "titreJp": "Kyoukai no Kanata",
      "img": "h8tsb",
      "ahId": "miscl",
      "addedAt": "2026-05-31T14:41:37.572Z"
    },
    {
      "titre": "Milky☆Subway: The Galactic Limited Express Movie",
      "titreJp": "Ginga Tokkyuu Milky☆Subway  Movie",
      "img": "t4w4x",
      "ahId": "at0k4",
      "addedAt": "2026-05-31T14:41:37.572Z"
    },
    {
      "titre": "Smoking Behind the Supermarket with You",
      "titreJp": "Super no Ura de Yani Suu Futari",
      "img": "z18pc",
      "ahId": "gnv5p",
      "addedAt": "2026-06-08T03:39:57.237Z"
    },
    {
      "titre": "Kakegurui Twin",
      "titreJp": "",
      "img": "0kqmq",
      "ahId": "zfnmd",
      "addedAt": "2026-06-09T22:21:31.616Z"
    },
    {
      "titre": "Cat Planet Cuties",
      "titreJp": "Asobi ni Iku yo!",
      "img": "b06ma",
      "ahId": "6p1bo",
      "addedAt": "2026-06-10T00:09:51.471Z"
    },
    {
      "titre": "My Roommate is a Cat",
      "titreJp": "Doukyonin wa Hiza, Tokidoki, Atama no Ue.",
      "img": "j3fa1",
      "ahId": "um43g",
      "addedAt": "2026-06-10T12:54:05.595Z"
    },
    {
      "titre": "Mr. Osomatsu 4th Season",
      "titreJp": "Osomatsu-san 4th Season",
      "img": "dn75y",
      "ahId": "cqu9c",
      "addedAt": "2026-06-11T19:33:16.825Z"
    },
    {
      "titre": "Girls' Last Tour",
      "titreJp": "Shoujo Shuumatsu Ryokou",
      "img": "3bxq0",
      "ahId": "x7nqp",
      "addedAt": "2026-06-14T23:05:35.673Z"
    },
    {
      "titre": "Tsuredure Children",
      "titreJp": "",
      "img": "un6gb",
      "ahId": "xyc65",
      "addedAt": "2026-06-15T23:00:20.070Z"
    },
    {
      "titre": "Log Horizon",
      "titreJp": "",
      "img": "t3zck",
      "ahId": "4aij9",
      "addedAt": "2026-06-16T03:43:53.502Z"
    },
    {
      "titre": "Log Horizon 2",
      "titreJp": "",
      "img": "9x7v7",
      "ahId": "0cezs",
      "addedAt": "2026-06-17T00:13:01.223Z"
    },
    {
      "titre": "Log Horizon: Destruction of the Round Table",
      "titreJp": "Log Horizon: Entaku Houkai",
      "img": "31uy2",
      "ahId": "rviy5",
      "addedAt": "2026-06-17T15:18:31.783Z"
    },
    {
      "titre": "When They Cry: Higurashi",
      "titreJp": "Higurashi no Naku Koro ni",
      "img": "k2u6q",
      "ahId": "govlg",
      "addedAt": "2026-06-17T21:02:03.805Z"
    },
    {
      "titre": "BAKI-DOU: The Invincible Samurai",
      "titreJp": "",
      "img": "ww5ij",
      "ahId": "5ebj0",
      "addedAt": "2026-06-18T12:21:57.602Z"
    },
    {
      "titre": "Zombie Land Saga",
      "titreJp": "",
      "img": "4uaqu",
      "ahId": "h4qss",
      "addedAt": "2026-06-19T19:45:03.055Z"
    },
    {
      "titre": "Zombie Land Saga Movie: Yumeginga Paradise",
      "titreJp": "",
      "img": "yb4l8",
      "ahId": "6t6r9",
      "addedAt": "2026-06-19T19:45:03.055Z"
    },
    {
      "titre": "Zombie Land Saga Revenge",
      "titreJp": "",
      "img": "vsiwj",
      "ahId": "25c5q",
      "addedAt": "2026-06-19T22:53:30.840Z"
    },
    {
      "titre": "Lord of Mysteries Specials",
      "titreJp": "Guimi Zhi Zhu Specials",
      "img": "5xaaz",
      "ahId": "okq7x",
      "addedAt": "2026-06-20T08:49:57.649Z"
    },
    {
      "titre": "Baka and Test - Summon the Beasts",
      "titreJp": "Baka to Test to Shoukanjuu",
      "img": "lcrl0",
      "ahId": "ah4rl",
      "addedAt": "2026-06-21T20:22:22.458Z"
    },
    {
      "titre": "Baka and Test - Summon the Beasts 2",
      "titreJp": "Baka to Test to Shoukanjuu Ni!",
      "img": "lh4j8",
      "ahId": "o8tj1",
      "addedAt": "2026-06-22T00:08:14.905Z"
    },
    {
      "titre": "Heroine? Saint? No, I’m an All-Works Maid (And Proud of It)!",
      "titreJp": "Heroine? Seijo? Iie, All Works Maid desu (Hokori)!",
      "img": "ycs89",
      "ahId": "q3n2b",
      "addedAt": "2026-06-24T18:49:01.569Z"
    },
    {
      "titre": "From Overshadowed to Overpowered: Second Reincarnation of a Talentless Sage",
      "titreJp": "Rakudai Kenja no Gakuin Musou: Nidome no Tensei, S-Rank Cheat Majutsushi Boukenroku, The Unsuccessful Yet Academically Unparalleled Sage: A Cheating S-Rank Sorcerer&#039;s Post-Rebirth Adventurer Log",
      "img": "cy9ca",
      "ahId": "ultkb",
      "addedAt": "2026-06-25T17:09:40.262Z"
    },
    {
      "titre": "That Time I Got Reincarnated as a Slime Movie 2: Tears of the Azure Sea",
      "titreJp": "Tensei Shitara Slime Datta Ken Movie 2: Soukai no Namida Hen",
      "img": "034lt",
      "ahId": "sa311",
      "addedAt": "2026-06-27T00:03:07.110Z"
    },
    {
      "titre": "Victoria of Many Faces",
      "titreJp": "Tefuda ga Oume no Victoria",
      "img": "zwc02",
      "ahId": "lckgk",
      "addedAt": "2026-06-27T12:06:51.062Z"
    },
    {
      "titre": "The Cat and the Dragon",
      "titreJp": "Neko to Ryuu",
      "img": "828yy",
      "ahId": "9zg3f",
      "addedAt": "2026-06-27T14:26:41.391Z"
    },
    {
      "titre": "Fate/stay night: Heaven's Feel Movies",
      "titreJp": "",
      "img": "xrngl",
      "ahId": "wbzq7",
      "addedAt": "2026-06-28T13:39:20.137Z"
    },
    {
      "titre": "The World Is Dancing",
      "titreJp": "World Is Dancing",
      "img": "ob8k9",
      "ahId": "jc70y",
      "addedAt": "2026-06-29T14:45:47.634Z"
    },
    {
      "titre": "Fate/Zero",
      "titreJp": "",
      "img": "2xov7",
      "ahId": "1xbu0",
      "addedAt": "2026-06-29T17:33:03.212Z"
    },
    {
      "titre": "The Oblivious Saint Can't Contain Her Power",
      "titreJp": "Mujikaku Seijo wa Kyou mo Muishiki ni Chikara wo Tarenagasu",
      "img": "fctsy",
      "ahId": "mvh9u",
      "addedAt": "2026-06-30T14:11:52.732Z"
    },
    {
      "titre": "The Yakuza's Guide to Babysitting",
      "titreJp": "Kumichou Musume to Sewagakari",
      "img": "sbvlf",
      "ahId": "jl4ns",
      "addedAt": "2026-06-30T17:04:26.234Z"
    },
    {
      "titre": "Hana-Kimi",
      "titreJp": "Hanazakari no Kimi-tachi e",
      "img": "futcv",
      "ahId": "bs07m",
      "addedAt": "2026-07-01T11:58:25.443Z"
    },
    {
      "titre": "Hana-Kimi Season 2",
      "titreJp": "Hanazakari no Kimi-tachi e Season 2",
      "img": "yzbv7",
      "ahId": "s3cd7",
      "addedAt": "2026-07-01T17:11:15.439Z"
    },
    {
      "titre": "The Villager of LV999",
      "titreJp": "LV999 no Murabito",
      "img": "7vqbp",
      "ahId": "mucnh",
      "addedAt": "2026-07-01T17:11:15.439Z"
    },
    {
      "titre": "Dara-san of Reiwa",
      "titreJp": "Reiwa no Dara-san",
      "img": "bkz60",
      "ahId": "59rhi",
      "addedAt": "2026-07-02T12:54:45.749Z"
    },
    {
      "titre": "BanG Dream! Yume∞Mita",
      "titreJp": "",
      "img": "8z55a",
      "ahId": "78byl",
      "addedAt": "2026-07-02T15:12:25.691Z"
    },
    {
      "titre": "Bungo Stray Dogs Wan!",
      "titreJp": "",
      "img": "ofyoh",
      "ahId": "rtmcg",
      "addedAt": "2026-07-02T15:12:25.691Z"
    },
    {
      "titre": "Bungo Stray Dogs Wan! 2",
      "titreJp": "",
      "img": "gob1n",
      "ahId": "1wtvp",
      "addedAt": "2026-07-02T15:12:25.691Z"
    },
    {
      "titre": "Chainsmoker Cat",
      "titreJp": "Yani Neko",
      "img": "r45h0",
      "ahId": "6hqka",
      "addedAt": "2026-07-02T17:43:17.516Z"
    },
    {
      "titre": "The Exiled Heavy Knight Knows How to Game the System",
      "titreJp": "Tsuihou sareta Tensei Juukishi wa Game Chishiki de Musou suru",
      "img": "3ks09",
      "ahId": "6uopw",
      "addedAt": "2026-07-02T17:43:17.517Z"
    },
    {
      "titre": "Kaiju Girl Caramelise",
      "titreJp": "Otome Kaijuu Caramelise, Meiden Kaiju Carameliser",
      "img": "gtz8g",
      "ahId": "wfsth",
      "addedAt": "2026-07-02T19:19:24.252Z"
    },
    {
      "titre": "Crowned in a Hundred Days",
      "titreJp": "Bai Ri Cheng Wang",
      "img": "c1n5b",
      "ahId": "z1cl4",
      "addedAt": "2026-07-03T06:28:24.112Z"
    },
    {
      "titre": "I Became a Legend after My 10 Year-Long Last Stand",
      "titreJp": "Koko wa Ore ni Makasete Saki ni Ike to Itte kara 10-nen ga Tattara Densetsu ni Natteita.",
      "img": "atd9e",
      "ahId": "4cpxl",
      "addedAt": "2026-07-03T15:07:56.036Z"
    },
    {
      "titre": "The Frontier Lord Begins with Zero Subjects",
      "titreJp": "Ryoumin 0-nin Start no Henkyou Ryoushu-sama",
      "img": "lq61b",
      "ahId": "wj4jh",
      "addedAt": "2026-07-03T15:07:56.036Z"
    },
    {
      "titre": "Hell Mode: The Hardcore Gamer Dominates in Another World with Garbage Balancing 2nd Season",
      "titreJp": "Hell Mode: Yarikomi Suki no Gamer wa Haisettei no Isekai de Musousuru - Hajimari no Shoukanshi 2nd Season",
      "img": "c5wg4",
      "ahId": "vnlfg",
      "addedAt": "2026-07-03T17:21:39.247Z"
    },
    {
      "titre": "Sorry About My Little Brothers",
      "titreJp": "Uchi no Otouto-domo ga Sumimasen",
      "img": "9jn5c",
      "ahId": "ldpso",
      "addedAt": "2026-07-03T17:21:39.247Z"
    },
    {
      "titre": "Draw this, then die!",
      "titreJp": "Kore Kaite Shine",
      "img": "6ku09",
      "ahId": "zc42w",
      "addedAt": "2026-07-03T17:21:39.247Z"
    },
    {
      "titre": "Kamui-san Directly Behind You",
      "titreJp": "Ushirou no Shoumen Kamui-san",
      "img": "e9nx0",
      "ahId": "cc9vg",
      "addedAt": "2026-07-03T21:01:11.516Z"
    },
    {
      "titre": "Skeleton Knight in Another World 2",
      "titreJp": "Gaikotsu Kishi-sama, Tadaima Isekai e Odekake-chuu II",
      "img": "3ol6v",
      "ahId": "1oaxo",
      "addedAt": "2026-07-04T12:04:39.107Z"
    },
    {
      "titre": "Mushoku Tensei: Jobless Reincarnation 3rd Season",
      "titreJp": "Mushoku Tensei III: Isekai Ittara Honki Dasu",
      "img": "b1dg7",
      "ahId": "sfvog",
      "addedAt": "2026-07-04T12:04:39.107Z"
    },
    {
      "titre": "Recommendations from Iwamoto-Senpai",
      "titreJp": "Iwamoto-senpai no Suisen",
      "img": "gnmlq",
      "ahId": "nn6k9",
      "addedAt": "2026-07-04T14:26:37.244Z"
    },
    {
      "titre": "Black Torch",
      "titreJp": "",
      "img": "xq99f",
      "ahId": "7tq84",
      "addedAt": "2026-07-04T14:26:37.244Z"
    },
    {
      "titre": "Jaadugar: A Witch in Mongolia",
      "titreJp": "Tenmaku no Jaadugar",
      "img": "9ihs5",
      "ahId": "t1ey0",
      "addedAt": "2026-07-04T17:13:54.663Z"
    },
    {
      "titre": "Rich Girl Caretaker: I'm Secretly the Caregiver of the Most Popular Girl in This Rich Kid School.",
      "titreJp": "Saijo no Osewa: Takane no Hana-darake na Meimonkou de, Gakuin Ichi no Ojou-sama (Seikatsu Nouryoku Kaimu) wo Kagenagara Osewasuru Koto ni Narimashita",
      "img": "bprh4",
      "ahId": "n2apg",
      "addedAt": "2026-07-04T19:05:39.710Z"
    },
    {
      "titre": "Magilumiere Co. Ltd. 2nd Season",
      "titreJp": "Kabushikigaisha Magi-Lumière 2nd Season",
      "img": "a0m9j",
      "ahId": "7776o",
      "addedAt": "2026-07-04T19:05:39.710Z"
    },
    {
      "titre": "Magilumiere Co. Ltd.",
      "titreJp": "Kabushikigaisha Magi-Lumière",
      "img": "jb5fh",
      "ahId": "52r9c",
      "addedAt": "2026-07-04T19:05:39.710Z"
    },
    {
      "titre": "Magical Girl Lyrical Nanoha EXCEEDS Gun Blaze Vengeance",
      "titreJp": "",
      "img": "zpm54",
      "ahId": "zweu6",
      "addedAt": "2026-07-04T19:05:39.710Z"
    },
    {
      "titre": "The Duke’s Son Claims He Won’t Love Me Yet Showers Me with Adoration",
      "titreJp": "\\&quot;Kimi wo Aisuru Ki wa Nai\\&quot; to Itta Jiki Koushaku-sama ga nazeka Dekiaishitekimasu",
      "img": "r5tg3",
      "ahId": "m6wg7",
      "addedAt": "2026-07-04T19:05:39.710Z"
    },
    {
      "titre": "The Ogre's Bride",
      "titreJp": "Oni no Hanayome",
      "img": "csu03",
      "ahId": "u6fdm",
      "addedAt": "2026-07-04T19:05:39.710Z"
    },
    {
      "titre": "The 100 Girlfriends Who Really, Really, Really, Really, Really Love You Season 2",
      "titreJp": "Kimi no Koto ga Daidaidaidaidaisuki na 100-nin no Kanojo 2nd Season",
      "img": "d4h4l",
      "ahId": "ahsr3",
      "addedAt": "2026-07-05T12:13:17.225Z"
    },
    {
      "titre": "You and I are Polar Opposites",
      "titreJp": "Seihantai na Kimi to Boku",
      "img": "dcend",
      "ahId": "90tky",
      "addedAt": "2026-07-05T12:13:17.225Z"
    },
    {
      "titre": "Iron Wok Jan!",
      "titreJp": "Tetsunabe no Jan!",
      "img": "5yj1u",
      "ahId": "3l7kl",
      "addedAt": "2026-07-05T12:13:17.225Z"
    },
    {
      "titre": "You and I are Polar Opposites 2nd Season",
      "titreJp": "Seihantai na Kimi to Boku 2nd Season",
      "img": "j1ir5",
      "ahId": "th5p2",
      "addedAt": "2026-07-05T12:13:17.225Z"
    },
    {
      "titre": "Let's Go Kaikigumi",
      "titreJp": "",
      "img": "03516",
      "ahId": "2ydm9",
      "addedAt": "2026-07-05T12:13:17.225Z"
    },
    {
      "titre": "The 100 Girlfriends Who Really, Really, Really, Really, Really Love You Season 3",
      "titreJp": "Kimi no Koto ga Daidaidaidaidaisuki na 100-nin no Kanojo 3rd Season",
      "img": "xtq52",
      "ahId": "atyey",
      "addedAt": "2026-07-05T14:38:36.892Z"
    },
    {
      "titre": "The World's Strongest Rearguard: Labyrinth Country's Novice Seeker",
      "titreJp": "Sekai Saikyou no Kouei: Meikyuukoku no Shinjin Tansakusha",
      "img": "tak3w",
      "ahId": "y01g1",
      "addedAt": "2026-07-05T14:38:36.892Z"
    },
    {
      "titre": "Goodbye, Lara",
      "titreJp": "Sayonara Lara",
      "img": "c5pih",
      "ahId": "f76b2",
      "addedAt": "2026-07-05T16:04:42.403Z"
    },
    {
      "titre": "Sparks of Tomorrow",
      "titreJp": "Nijusseiki Denki Mokuroku: Eureka Evrika, 20 Seiki Denki Mokuroku: Eureka Evrika",
      "img": "2e371",
      "ahId": "1wghj",
      "addedAt": "2026-07-05T16:04:42.403Z"
    },
    {
      "titre": "One Piece Heroines",
      "titreJp": "",
      "img": "giul6",
      "ahId": "ckqsc",
      "addedAt": "2026-07-05T17:59:28.237Z"
    },
    {
      "titre": "Azur Lane",
      "titreJp": "",
      "img": "g8puj",
      "ahId": "yjv4a",
      "addedAt": "2026-07-05T20:55:32.229Z"
    },
    {
      "titre": "Azur Lane: Slow Ahead!",
      "titreJp": "Azur Lane: Bisoku Zenshin!",
      "img": "butmb",
      "ahId": "zxy6h",
      "addedAt": "2026-07-05T20:55:32.229Z"
    },
    {
      "titre": "Azur Lane: Slow Ahead! 2nd Season",
      "titreJp": "Azur Lane: Bisoku Zenshin! 2nd Season",
      "img": "8j4y6",
      "ahId": "marhn",
      "addedAt": "2026-07-05T20:55:32.229Z"
    },
    {
      "titre": "Bloom Into You",
      "titreJp": "Yagate Kimi ni Naru",
      "img": "jfrlj",
      "ahId": "odbas",
      "addedAt": "2026-07-05T23:10:11.228Z"
    },
    {
      "titre": "Grand Blue Season 3",
      "titreJp": "Grand Blue Dreaming Season 3",
      "img": "o5w0q",
      "ahId": "gwokm",
      "addedAt": "2026-07-06T16:17:54.424Z"
    },
    {
      "titre": "A Livid Lady's Guide to Getting Even: How I Crushed My Homeland with My Mighty Grimoires",
      "titreJp": "Buchikire Reijou wa Houfuku wo Chikai Mashita. Madousho no Chikara de Sokoku wo Tataki Tsubushimasu",
      "img": "s5q25",
      "ahId": "o0cpo",
      "addedAt": "2026-07-06T16:17:54.424Z"
    },
    {
      "titre": "Oh Boy, Was I Wrong About Her",
      "titreJp": "Tenkousaki no Seiso Karen na Bishoujo ga, Mukashi Danshi to Omotte Issho ni Asonda Osananajimi datta Ken",
      "img": "vse6w",
      "ahId": "7e6hd",
      "addedAt": "2026-07-06T16:17:54.424Z"
    },
    {
      "titre": "The Forsaken Saintess and Her Foodie Roadtrip in Another World",
      "titreJp": "Suterare Seijo no Isekai Gohan Tabi: Kakure Skill de Camping Car wo Shoukan Shimashita",
      "img": "0vaar",
      "ahId": "x2njz",
      "addedAt": "2026-07-06T16:17:54.424Z"
    },
    {
      "titre": "The Insipid Prince's Furtive Grab for The Throne",
      "titreJp": "Saikyou Degarashi Ouji no Anyaku Teii Arasoi, The Strongest Dull Prince&#039;s Secret Battle for the Throne",
      "img": "lzwax",
      "ahId": "jdq4y",
      "addedAt": "2026-07-06T16:17:54.424Z"
    },
    {
      "titre": "Love Unseen Beneath the Clear Night Sky",
      "titreJp": "Toumei na Yoru ni Kakeru Kimi to, Me ni Mienai Koi wo Shita.",
      "img": "2qfc1",
      "ahId": "fn31g",
      "addedAt": "2026-07-06T16:17:54.424Z"
    },
    {
      "titre": "Young Ladies Don't Play Fighting Games",
      "titreJp": "Tai-Ari deshita. Ojou-sama wa Kakutou Game Nante Shinai",
      "img": "q69uk",
      "ahId": "vgurt",
      "addedAt": "2026-07-07T11:45:41.218Z"
    },
    {
      "titre": "I Want to Love You Till Your Dying Day",
      "titreJp": "Kimi ga Shinu made Koi wo Shitai",
      "img": "5kivb",
      "ahId": "f6u2m",
      "addedAt": "2026-07-07T14:24:35.344Z"
    },
    {
      "titre": "Yoroi-Shinden Samurai Troopers",
      "titreJp": "Yoroi Shin Den Samurai Troopers, Ronin Warriors",
      "img": "po8jo",
      "ahId": "bzdq4",
      "addedAt": "2026-07-07T14:24:35.344Z"
    },
    {
      "titre": "The Ghost in the Shell",
      "titreJp": "Koukaku Kidoutai: The Ghost in the Shell",
      "img": "8vo2j",
      "ahId": "nqbd0",
      "addedAt": "2026-07-07T19:50:19.305Z"
    },
    {
      "titre": "Flaming Dodgeball Girl Danko",
      "titreJp": "Honoo no Toukyuujo: Dodge Danko",
      "img": "t7nlu",
      "ahId": "usbqy",
      "addedAt": "2026-07-07T19:50:19.305Z"
    },
    {
      "titre": "Red River",
      "titreJp": "Sora wa Akai Kawa no Hotori",
      "img": "zh355",
      "ahId": "x48y1",
      "addedAt": "2026-07-07T19:50:19.305Z"
    },
    {
      "titre": "Yoroi-Shinden Samurai Troopers - Part II",
      "titreJp": "Yoroi Shin Den Samurai Troopers - Part II, Ronin Warriors - Part II",
      "img": "pnulh",
      "ahId": "2oq0n",
      "addedAt": "2026-07-07T19:50:19.305Z"
    },
    {
      "titre": "Clevatess Season 2",
      "titreJp": "Clevatess 2: Majuu no Ou to Akago to Shikabane no Yuusha,",
      "img": "lz0uu",
      "ahId": "d99rj",
      "addedAt": "2026-07-08T12:17:38.869Z"
    },
    {
      "titre": "My Stepmother and Stepsisters Aren’t Wicked",
      "titreJp": "Ibitte Konai Gibo to Gishi",
      "img": "b8zqi",
      "ahId": "8e1k6",
      "addedAt": "2026-07-08T15:17:46.142Z"
    },
    {
      "titre": "Saga of Tanya the Evil II",
      "titreJp": "",
      "img": "wr5w2",
      "ahId": "jrus1",
      "addedAt": "2026-07-08T15:17:46.142Z"
    },
    {
      "titre": "From Old Country Bumpkin to Master Swordsman Season 2",
      "titreJp": "Katainaka no Ossan, Kensei ni Naru II",
      "img": "8yx8x",
      "ahId": "hoi3i",
      "addedAt": "2026-07-08T17:25:38.914Z"
    },
    {
      "titre": "Trapped in a Dating Sim: The World of Otome Games is Tough for Mobs 2nd Season",
      "titreJp": "Otomege Sekai wa Mob ni Kibishii Sekai Desu 2nd Season",
      "img": "l7tno",
      "ahId": "6rmgo",
      "addedAt": "2026-07-08T17:25:38.914Z"
    },
    {
      "titre": "Tomb Raider King",
      "titreJp": "Dogurwang",
      "img": "1i8dr",
      "ahId": "7p85t",
      "addedAt": "2026-07-08T19:19:41.071Z"
    },
    {
      "titre": "Mebius Dust",
      "titreJp": "",
      "img": "02htn",
      "ahId": "yv7me",
      "addedAt": "2026-07-09T16:25:04.906Z"
    }
  ],
  "updatedAt": "2026-07-10T20:19:39.184Z",
  "count": 189
}